.travis.yml
MANIFEST.in
README.rst
bootstrap.py
buildout.cfg
setup.cfg
setup.py
travis.cfg
.tx/config
docs/HISTORY.rst
docs/INSTALL.rst
docs/LICENSE.GPL
docs/LICENSE.txt
quintagroup/__init__.py
quintagroup.seoptimizer.egg-info/PKG-INFO
quintagroup.seoptimizer.egg-info/SOURCES.txt
quintagroup.seoptimizer.egg-info/dependency_links.txt
quintagroup.seoptimizer.egg-info/entry_points.txt
quintagroup.seoptimizer.egg-info/namespace_packages.txt
quintagroup.seoptimizer.egg-info/not-zip-safe
quintagroup.seoptimizer.egg-info/requires.txt
quintagroup.seoptimizer.egg-info/top_level.txt
quintagroup/seoptimizer/README.txt
quintagroup/seoptimizer/__init__.py
quintagroup/seoptimizer/adapters.py
quintagroup/seoptimizer/adapters.zcml
quintagroup/seoptimizer/config.py
quintagroup/seoptimizer/configure.zcml
quintagroup/seoptimizer/interfaces.py
quintagroup/seoptimizer/listMetaTags.py
quintagroup/seoptimizer/overrides.zcml
quintagroup/seoptimizer/patches.zcml
quintagroup/seoptimizer/profiles.zcml
quintagroup/seoptimizer/setuphandlers.py
quintagroup/seoptimizer/upgrades.py
quintagroup/seoptimizer/util.py
quintagroup/seoptimizer/Extensions/Install.py
quintagroup/seoptimizer/browser/__init__.py
quintagroup/seoptimizer/browser/configure.zcml
quintagroup/seoptimizer/browser/interfaces.py
quintagroup/seoptimizer/browser/keywords.py
quintagroup/seoptimizer/browser/seo_configlet.py
quintagroup/seoptimizer/browser/seo_icon.gif
quintagroup/seoptimizer/browser/viewlets.py
quintagroup/seoptimizer/browser/views.py
quintagroup/seoptimizer/browser/resources/seo_context_properties.js
quintagroup/seoptimizer/browser/resources/seo_icon.gif
quintagroup/seoptimizer/browser/templates/seo_context_properties.pt
quintagroup/seoptimizer/locales/quintagroup.seoptimizer.pot
quintagroup/seoptimizer/locales/es/LC_MESSAGES/quintagroup.seoptimizer.mo
quintagroup/seoptimizer/locales/es/LC_MESSAGES/quintagroup.seoptimizer.po
quintagroup/seoptimizer/locales/fr/LC_MESSAGES/quintagroup.seoptimizer.mo
quintagroup/seoptimizer/locales/fr/LC_MESSAGES/quintagroup.seoptimizer.po
quintagroup/seoptimizer/locales/uk/LC_MESSAGES/quintagroup.seoptimizer.po
quintagroup/seoptimizer/profiles/default/actionicons.xml
quintagroup/seoptimizer/profiles/default/actions.xml
quintagroup/seoptimizer/profiles/default/browserlayer.xml
quintagroup/seoptimizer/profiles/default/controlpanel.xml
