Metadata-Version: 1.0
Name: quintagroup.seoptimizer
Version: 4.3
Summary: Quintagroup Search Engine Optimization Tool
Home-page: http://quintagroup.com/services/plone-development/products/qSEOptimizer/
Author: Myroslav Opyr, Volodymyr Romaniuk, Mykola Kharechko, Vitaliy Podoba, Volodymyr Cherepanyak, Taras Melnychuk, Vitaliy Stepanov, Andriy Mylenkyy
Author-email: support@quintagroup.com
License: GPL
Keywords: web zope plone seo search optimization
Platform: UNKNOWN
Classifier: Framework :: Plone
Classifier: Framework :: Plone :: 3.2
Classifier: Framework :: Plone :: 3.3
Classifier: Framework :: Plone :: 4.0
Classifier: Framework :: Plone :: 4.1
Classifier: Framework :: Plone :: 4.2
Classifier: Framework :: Plone :: 4.3
Classifier: Framework :: Zope2
Classifier: Framework :: Zope3
Classifier: Programming Language :: Python
Classifier: Topic :: Software Development :: Libraries :: Python Modules
Classifier: License :: OSI Approved :: GNU General Public License (GPL)
Classifier: Topic :: Internet :: WWW/HTTP :: Indexing/Search
Classifier: Operating System :: OS Independent
Classifier: Development Status :: 5 - Production/Stable
